LICENSE
astropic/__init__.py
astropic/fits2png.py
astropic/main.py
astropic-1.1.6.dist-info/LICENSE
astropic-1.1.6.dist-info/WHEEL
astropic-1.1.6.dist-info/METADATA
astropic-1.1.6.dist-info/RECORD
